ytube/__init__.py
ytube/custom_exeptions.py
ytube/downloader.py
ytube/model.py
pytube_downloader-1.0.1.dist-info/LICENSE
pytube_downloader-1.0.1.dist-info/METADATA
pytube_downloader-1.0.1.dist-info/WHEEL
pytube_downloader-1.0.1.dist-info/top_level.txt
pytube_downloader-1.0.1.dist-info/RECORD
