Metadata-Version: 2.1
Name: pytube-downloader
Version: 1.0.1
Summary: Wrapper over pytube python's package
Home-page: https://github.com/shubhamraj2202/pytube-downloader
Author: Shubham Raj
Author-email: shubhamraj2202@gmail.com
Project-URL: Bug Reports, https://github.com/shubhamraj2202/pytube-downloader/issues
License-File: LICENSE
Requires-Dist: pytube
Requires-Dist: pyhelper-misc
Requires-Dist: pydantic
